smarttub/__init__.py
smarttub/__main__.py
smarttub/api.py
python_smarttub-0.0.45.dist-info/METADATA
python_smarttub-0.0.45.dist-info/WHEEL
python_smarttub-0.0.45.dist-info/licenses/LICENSE
python_smarttub-0.0.45.dist-info/RECORD
