Metadata-Version: 2.4
Name: python-smarttub
Version: 0.0.45
Summary: API to query and control hot tubs using the SmartTub system
License: MIT
License-File: LICENSE
Requires-Python: >=3.9
Requires-Dist: aiohttp>=3.9.1
Requires-Dist: inflection~=0.5.1
Requires-Dist: pyjwt>=2.10.0
Requires-Dist: python-dateutil>=2.8.1
Provides-Extra: dev
Requires-Dist: aresponses; extra == 'dev'
Requires-Dist: black; extra == 'dev'
Requires-Dist: flake8; extra == 'dev'
Requires-Dist: pre-commit; extra == 'dev'
Requires-Dist: pytest; extra == 'dev'
Requires-Dist: pytest-asyncio; extra == 'dev'
Requires-Dist: pytest-cov; extra == 'dev'
Requires-Dist: twine; extra == 'dev'
